Metadata-Version: 1.0
Name: stat-distributions
Version: 0.1
Summary: Gaussian and Binomial distributions
Home-page: UNKNOWN
Author: Nelson Tsaku
Author-email: UNKNOWN
License: UNKNOWN
Platform: UNKNOWN
